setup.py
./zopaclient/__init__.py
./zopaclient/api.py
./zopaclient/log.py
zopaClient.egg-info/PKG-INFO
zopaClient.egg-info/SOURCES.txt
zopaClient.egg-info/dependency_links.txt
zopaClient.egg-info/top_level.txt