Metadata-Version: 1.1
Name: zopaClient
Version: 2.0.1
Summary: python library for Zopa.com
Home-page: https://github.com/jfparis/ZopaClient
Author: Jean-Francois Paris
Author-email: jfparis@rouge.eu.org
License: LGPL 2.0
Platform: UNKNOWN
Classifier: Development Status :: 5 - Production/Stable
Classifier: Intended Audience :: Developers
Classifier: Natural Language :: English
Classifier: License :: OSI Approved :: GNU Lesser General Public License v3 or later (LGPLv3+)
Classifier: Programming Language :: Python
Classifier: Programming Language :: Python :: 2.7
Classifier: Programming Language :: Python :: 3
Classifier: Programming Language :: Python :: 3.4
Requires: lxml
Requires: requests
Requires: cssselect
